{
  "All_Order_Details": [
    {
      "Date_field": "15-Jul-2021",
      "Customer_Name": "Sri Sai Super Market",
      "Total": "2259.43",
      "Sub_Total": "2061.00",
      "ID": "100584000000118223",
      "Central_Tax": "99.22",
      "Products.Stock_Item": "Idhayam 500ml,2,304.00,Idhayam 1litre,5,1255.00,Vanaspati Ghee,2,502.00",
      "State_Tax": "99.22"
    },
    {
      "Date_field": "15-Jul-2021",
      "Customer_Name": "ID Retail Shop",
      "Total": "2123.10",
      "Sub_Total": "2022.00",
      "ID": "100584000000118207",
      "Central_Tax": "50.55",
      "Products.Stock_Item": "Idhayam 1litre,2,502.00,Idhayam 500ml,10,1520.00",
      "State_Tax": "50.55"
    },
    {
      "Date_field": "15-Jul-2021",
      "Customer_Name": "Gensys Retail Shop",
      "Total": "2123.10",
      "Sub_Total": "2022.00",
      "ID": "100584000000118195",
      "Central_Tax": "50.55",
      "Products.Stock_Item": "Idhayam 1litre,2,502.00,Idhayam 500ml,10,1520.00",
      "State_Tax": "50.55"
    },
    {
      "Date_field": "15-Jul-2021",
      "Customer_Name": "Phantom Shop",
      "Total": "5827.50",
      "Sub_Total": "5550.00",
      "ID": "100584000000118183",
      "Central_Tax": "138.75",
      "Products.Stock_Item": "Idhayam 500ml,20,3040.00,Idhayam 1litre,10,2510.00",
      "State_Tax": "138.75"
    },
    {
      "Date_field": "15-Jul-2021",
      "Customer_Name": "ID Retail Shop",
      "Total": "263.55",
      "Sub_Total": "251.00",
      "ID": "100584000000118171",
      "Central_Tax": "6.28",
      "Products.Stock_Item": "Idhayam 1litre,1,251.00",
      "State_Tax": "6.28"
    },
    {
      "Date_field": "15-Jul-2021",
      "Customer_Name": "Phantom Shop",
      "Total": "159.60",
      "Sub_Total": "152.00",
      "ID": "100584000000118163",
      "Central_Tax": "3.80",
      "Products.Stock_Item": "Idhayam 500ml,1,152.00",
      "State_Tax": "3.80"
    },
    {
      "Date_field": "15-Jul-2021",
      "Customer_Name": "Sri Sai Super Market",
      "Total": "3272.00",
      "Sub_Total": "2662.00",
      "ID": "100584000000118155",
      "Central_Tax": "305.00",
      "Products.Stock_Item": "Idhayam 500ml,1,152.00,Vanaspati Ghee,10,2510.00",
      "State_Tax": "305.00"
    },
    {
      "Date_field": "15-Jul-2021",
      "Customer_Name": "Sri Sai Super Market",
      "Total": "3894.48",
      "Sub_Total": "3164.00",
      "ID": "100584000000118143",
      "Central_Tax": "365.24",
      "Products.Stock_Item": "Idhayam 500ml,1,152.00,Vanaspati Ghee,12,3012.00",
      "State_Tax": "365.24"
    },
    {
      "Date_field": "15-Jul-2021",
      "Customer_Name": "Venkateshwara Retail Shop",
      "Total": "1404.56",
      "Sub_Total": "1156.00",
      "ID": "100584000000118131",
      "Central_Tax": "124.28",
      "Products.Stock_Item": "Idhayam 500ml,1,152.00,Vanaspati Ghee,4,1004.00",
      "State_Tax": "124.28"
    },
    {
      "Date_field": "15-Jul-2021",
      "Customer_Name": "ID Retail Shop",
      "Total": "2635.50",
      "Sub_Total": "2510.00",
      "ID": "100584000000118119",
      "Central_Tax": "62.75",
      "Products.Stock_Item": "Idhayam 1litre,10,2510.00",
      "State_Tax": "62.75"
    },
    {
      "Date_field": "15-Jul-2021",
      "Customer_Name": "Phantom Shop",
      "Total": "1093.32",
      "Sub_Total": "905.00",
      "ID": "100584000000118111",
      "Central_Tax": "94.16",
      "Products.Stock_Item": "Idhayam 500ml,1,152.00,Vanaspati Ghee,3,753.00",
      "State_Tax": "94.16"
    },
    {
      "Date_field": "15-Jul-2021",
      "Customer_Name": "Sri Sai Super Market",
      "Total": "2138.95",
      "Sub_Total": "1810.00",
      "ID": "100584000000118099",
      "Central_Tax": "164.48",
      "Products.Stock_Item": "Idhayam 500ml,2,304.00,Idhayam 1litre,1,251.00,Vanaspati Ghee,5,1255.00",
      "State_Tax": "164.48"
    },
    {
      "Date_field": "15-Jul-2021",
      "Customer_Name": "Sri Sai Super Market",
      "Total": "630.44",
      "Sub_Total": "555.00",
      "ID": "100584000000118083",
      "Central_Tax": "37.72",
      "Products.Stock_Item": "Vanaspati Ghee,1,251.00,Idhayam 500ml,2,304.00",
      "State_Tax": "37.72"
    },
    {
      "Date_field": "15-Jul-2021",
      "Customer_Name": "Sri Sai Super Market",
      "Total": "1420.48",
      "Sub_Total": "1262.00",
      "ID": "100584000000118071",
      "Central_Tax": "79.24",
      "Products.Stock_Item": "Idhayam 500ml,5,760.00,Vanaspati Ghee,2,502.00",
      "State_Tax": "79.24"
    },
    {
      "Date_field": "15-Jul-2021",
      "Customer_Name": "Phantom Shop",
      "Total": "1373.40",
      "Sub_Total": "1308.00",
      "ID": "100584000000118059",
      "Central_Tax": "32.70",
      "Products.Stock_Item": "Idhayam 500ml,2,304.00,Idhayam 1litre,4,1004.00",
      "State_Tax": "32.70"
    },
    {
      "Date_field": "15-Jul-2021",
      "Customer_Name": "Gensys Retail Shop",
      "Total": "638.40",
      "Sub_Total": "608.00",
      "ID": "100584000000118047",
      "Central_Tax": "15.20",
      "Products.Stock_Item": "Idhayam 500ml,4,608.00",
      "State_Tax": "15.20"
    },
    {
      "Date_field": "15-Jul-2021",
      "Customer_Name": "ID Retail Shop",
      "Total": "8139.60",
      "Sub_Total": "7752.00",
      "ID": "100584000000118039",
      "Central_Tax": "193.80",
      "Products.Stock_Item": "Idhayam 500ml,51,7752.00",
      "State_Tax": "193.80"
    }
  ]
}
